{
	"metaData" : {
		"sourceRevision" : "200209200000Z"
	},
	"objects" : [
		{
			"@objectName" : "CISCO-FABRIC-C12K-MIB::ciscoFabricC12kMIBFabMasterSchCh",
			"certification" : "STANDARD",
			"description" : [
				"This notification is generated when master scheduler",
				"on the system changes. It typically indicates the ",
				"switchover of the scheduler card. ",
				"cfcGenericGlobalFabMasterSched represents the ",
				"entPhysicalIndex of the new master scheduler card, ",
				"while entPhysicalName represents the entity physical ",
				"name of the card. The case of all scheduler cards going",
				"down would be represented by a value 0 for the ",
				"cfcGenericGlobalFabMasterSched and noSuchInstance for the",
				"entPhysicalName."
			],
			"domain" : "FAULT",
			"event" : {
				"EventCategory" : 3,
				"EventType" : "ciscoFabricC12kMIBFabMasterSchCh",
				"ExpireTime" : 3600,
				"Severity" : 2,
				"SubNode" : "Device",
				"Summary" : "Master scheduler card has switched over to $v2"
			},
			"metaData" : {
				"certified" : true
			},
			"method" : "trap",
			"test" : "$SNMPTRAPCMD CISCO-FABRIC-C12K-MIB::ciscoFabricC12kMIBFabMasterSchCh CISCO-FABRIC-C12K-MIB::cfcGenericGlobalFabMasterSched i 9999 ENTITY-MIB::entPhysicalName s EXAMPLE",
			"trap" : {
				"name" : "CISCO-FABRIC-C12K-MIB::ciscoFabricC12kMIBFabMasterSchCh",
				"oid" : "1.3.6.1.4.1.9.9.281.0.1",
				"variables" : [
					{
						"name" : "CISCO-FABRIC-C12K-MIB::cfcGenericGlobalFabMasterSched",
						"oid" : "1.3.6.1.4.1.9.9.281.1.1.1.2",
						"valueType" : "OCTET STRING"
					},
					{
						"name" : "ENTITY-MIB::entPhysicalName",
						"oid" : "1.3.6.1.2.1.47.1.1.1.1.7",
						"valueType" : "OCTET STRING"
					}
				]
			}
		}
	]
}